oureliza/__init__.py
oureliza/eliza.py
oureliza-1.2.0.dist-info/METADATA
oureliza-1.2.0.dist-info/WHEEL
oureliza-1.2.0.dist-info/RECORD
