Metadata-Version: 2.1
Name: oureliza
Version: 1.2.0
Summary: Minimal Python implementation of the ELIZA chatbot
Home-page: https://github.com/craigtrim/oureliza
Keywords: chatbot,eliza,nlp
Author: Craig Trim
Author-email: craigtrim@gmail.com
Requires-Python: >=3.8,<4.0
Classifier: Programming Language :: Python :: 3
Classifier: Programming Language :: Python :: 3.8
Classifier: Programming Language :: Python :: 3.9
Classifier: Programming Language :: Python :: 3.10
Classifier: Programming Language :: Python :: 3.11
Classifier: Programming Language :: Python :: 3.12
Project-URL: Repository, https://github.com/craigtrim/oureliza
